{
  "countDivergences": [],
  "evaluatorBlockCount": 32,
  "evaluatorOrphans": [],
  "gapsPushCount": 32,
  "matches": [
    {
      "evaluatorBlockName": "VD-1",
      "evaluatorCommentLine": 4650,
      "matchConfidence": 0.583,
      "matchMethod": "similarity",
      "registryId": "gap-vd-1-mechanical-valve-anticoag",
      "registryLine": 264
    },
    {
      "evaluatorBlockName": "VD-2",
      "evaluatorCommentLine": 4964,
      "matchConfidence": 0.667,
      "matchMethod": "similarity",
      "registryId": "gap-vd-2-bioprosthetic-echo",
      "registryLine": 360
    },
    {
      "evaluatorBlockName": "VD-3",
      "evaluatorCommentLine": 5231,
      "matchConfidence": 0.667,
      "matchMethod": "similarity",
      "registryId": "gap-vd-3-inr-monitoring",
      "registryLine": 876
    },
    {
      "evaluatorBlockName": "VD-4",
      "evaluatorCommentLine": 5264,
      "matchConfidence": 0.6,
      "matchMethod": "similarity",
      "registryId": "gap-vd-4-mitral-stenosis",
      "registryLine": 888
    },
    {
      "evaluatorBlockName": "VD-5",
      "evaluatorCommentLine": 5294,
      "matchConfidence": 0.6,
      "matchMethod": "similarity",
      "registryId": "gap-vd-5-aortic-regurgitation",
      "registryLine": 900
    },
    {
      "evaluatorBlockName": "VD-6",
      "evaluatorCommentLine": 5324,
      "matchConfidence": 0.667,
      "matchMethod": "similarity",
      "registryId": "gap-vd-6-doac-mechanical-valve",
      "registryLine": 912
    },
    {
      "evaluatorBlockName": "VD-7",
      "evaluatorCommentLine": 5354,
      "matchConfidence": 0.667,
      "matchMethod": "similarity",
      "registryId": "gap-vd-7-exercise-restriction-as",
      "registryLine": 924
    },
    {
      "evaluatorBlockName": "VD-8",
      "evaluatorCommentLine": 5383,
      "matchConfidence": 0.667,
      "matchMethod": "similarity",
      "registryId": "gap-vd-8-rheumatic-screen",
      "registryLine": 936
    },
    {
      "evaluatorBlockName": "VD-9",
      "evaluatorCommentLine": 5413,
      "matchConfidence": 0.5,
      "matchMethod": "similarity",
      "registryId": "gap-vd-9-endocarditis-education",
      "registryLine": 948
    },
    {
      "evaluatorBlockName": "VD-10",
      "evaluatorCommentLine": 5440,
      "matchConfidence": 0.714,
      "matchMethod": "similarity",
      "registryId": "gap-vd-10-pregnancy-risk",
      "registryLine": 960
    },
    {
      "evaluatorBlockName": "VD-11",
      "evaluatorCommentLine": 5472,
      "matchConfidence": 0.714,
      "matchMethod": "similarity",
      "registryId": "gap-vd-11-bioprosthetic-degeneration",
      "registryLine": 972
    },
    {
      "evaluatorBlockName": "VD-12",
      "evaluatorCommentLine": 5502,
      "matchConfidence": 0.786,
      "matchMethod": "similarity",
      "registryId": "gap-vd-12-af-valve-anticoag",
      "registryLine": 984
    },
    {
      "evaluatorBlockName": "VD-13",
      "evaluatorCommentLine": 6308,
      "matchConfidence": 0.875,
      "matchMethod": "similarity",
      "registryId": "gap-vd-13-anticoag-first3mo",
      "registryLine": 1656
    },
    {
      "evaluatorBlockName": "VD-14",
      "evaluatorCommentLine": 6342,
      "matchConfidence": 0.75,
      "matchMethod": "similarity",
      "registryId": "gap-vd-14-dental-prophylaxis",
      "registryLine": 1668
    },
    {
      "evaluatorBlockName": "VD-15",
      "evaluatorCommentLine": 6375,
      "matchConfidence": 0.714,
      "matchMethod": "similarity",
      "registryId": "gap-vd-15-aortic-root",
      "registryLine": 1680
    },
    {
      "evaluatorBlockName": "VD-16",
      "evaluatorCommentLine": 6404,
      "matchConfidence": 0.714,
      "matchMethod": "similarity",
      "registryId": "gap-vd-16-mixed-valve",
      "registryLine": 1692
    },
    {
      "evaluatorBlockName": "VD-17",
      "evaluatorCommentLine": 6430,
      "matchConfidence": 0.714,
      "matchMethod": "similarity",
      "registryId": "gap-vd-17-hemolysis",
      "registryLine": 1704
    },
    {
      "evaluatorBlockName": "VD-18",
      "evaluatorCommentLine": 6461,
      "matchConfidence": 0.778,
      "matchMethod": "similarity",
      "registryId": "gap-vd-18-exercise-testing",
      "registryLine": 1716
    },
    {
      "evaluatorBlockName": "VD-PANNUS",
      "evaluatorCommentLine": 10426,
      "matchConfidence": 0.643,
      "matchMethod": "similarity",
      "registryId": "gap-vd-prosthetic-pannus",
      "registryLine": 2184
    },
    {
      "evaluatorBlockName": "VD-RADIATION",
      "evaluatorCommentLine": 10459,
      "matchConfidence": 0.667,
      "matchMethod": "similarity",
      "registryId": "gap-vd-radiation-valve",
      "registryLine": 2196
    },
    {
      "evaluatorBlockName": "VD-ENDOCARDITIS-SURV",
      "evaluatorCommentLine": 10492,
      "matchConfidence": 0.583,
      "matchMethod": "similarity",
      "registryId": "gap-vd-infective-endo",
      "registryLine": 2208
    },
    {
      "evaluatorBlockName": "VD-BICUSPID-AORTOPATHY",
      "evaluatorCommentLine": 10524,
      "matchConfidence": 0.667,
      "matchMethod": "similarity",
      "registryId": "gap-vd-bicuspid-aneurysm",
      "registryLine": 2220
    },
    {
      "evaluatorBlockName": "VD-ANTICOAG-REVERSAL",
      "evaluatorCommentLine": 10556,
      "matchConfidence": 0.571,
      "matchMethod": "similarity",
      "registryId": "gap-vd-anticoag-reversal",
      "registryLine": 2232
    },
    {
      "evaluatorBlockName": "VD-TRANSCATHETER-MV",
      "evaluatorCommentLine": 10585,
      "matchConfidence": 0.714,
      "matchMethod": "similarity",
      "registryId": "gap-vd-transcatheter-mv",
      "registryLine": 2244
    },
    {
      "evaluatorBlockName": "VD-RHC",
      "evaluatorCommentLine": 10619,
      "matchConfidence": 0.563,
      "matchMethod": "similarity",
      "registryId": "gap-vd-right-heart-cath",
      "registryLine": 2256
    },
    {
      "evaluatorBlockName": "VD-VALVE-CLINIC",
      "evaluatorCommentLine": 10651,
      "matchConfidence": 0.667,
      "matchMethod": "similarity",
      "registryId": "gap-vd-valve-clinic-referral",
      "registryLine": 2268
    },
    {
      "evaluatorBlockName": "VD-ECHO-INTERVAL",
      "evaluatorCommentLine": 10693,
      "matchConfidence": 0.667,
      "matchMethod": "similarity",
      "registryId": "gap-vd-echo-interval",
      "registryLine": 3132
    },
    {
      "evaluatorBlockName": "VD-FUNCTIONAL-STATUS",
      "evaluatorCommentLine": 10724,
      "matchConfidence": 0.714,
      "matchMethod": "similarity",
      "registryId": "gap-vd-functional-status",
      "registryLine": 3144
    },
    {
      "evaluatorBlockName": "VD-PREOP-ASSESSMENT",
      "evaluatorCommentLine": 10756,
      "matchConfidence": 0.714,
      "matchMethod": "similarity",
      "registryId": "gap-vd-preop-assessment",
      "registryLine": 3156
    },
    {
      "evaluatorBlockName": "VD-PULMONARY-HTN",
      "evaluatorCommentLine": 10785,
      "matchConfidence": 0.75,
      "matchMethod": "similarity",
      "registryId": "gap-vd-pulmonary-htn",
      "registryLine": 3168
    },
    {
      "evaluatorBlockName": "VD-TRICUSPID-SECONDARY",
      "evaluatorCommentLine": 10817,
      "matchConfidence": 0.6,
      "matchMethod": "similarity",
      "registryId": "gap-vd-tricuspid-secondary",
      "registryLine": 3180
    },
    {
      "evaluatorBlockName": "VD-ANTIPLATELET-BIOPROSTHETIC",
      "evaluatorCommentLine": 10849,
      "matchConfidence": 0.5,
      "matchMethod": "similarity",
      "registryId": "gap-vd-antiplatelet-bioprosthetic",
      "registryLine": 3192
    }
  ],
  "module": "VHD",
  "namingMismatches": [],
  "registryCount": 32,
  "registryOrphans": [],
  "specGapCount": 105,
  "status": "CLEAN"
}
